README.md
setup.py
pirlpay/__init__.py
pirlpay/api_client.py
pirlpay/configuration.py
pirlpay/rest.py
pirlpay.egg-info/PKG-INFO
pirlpay.egg-info/SOURCES.txt
pirlpay.egg-info/dependency_links.txt
pirlpay.egg-info/requires.txt
pirlpay.egg-info/top_level.txt
pirlpay/pirlpay/__init__.py
pirlpay/pirlpay/billing_api.py
pirlpay/pirlpay/billing_plan.py
pirlpay/pirlpay/catalogs_api.py
pirlpay/pirlpay/payments_api.py
pirlpay/pirlpay/product.py
pirlpay/pirlpay/product_transaction.py
pirlpay/pirlpay/simple_payment.py
pirlpay/pirlpay/simple_payment_get.py
pirlpay/pirlpay/subscription.py
pirlpay/pirlpay/subscription_transaction.py
test/__init__.py
test/test_billing_api.py
test/test_billing_plan.py
test/test_catalogs_api.py
test/test_payments_api.py
test/test_product.py
test/test_product_transaction.py
test/test_simple_payment.py
test/test_simple_payment_get.py
test/test_subscription.py
test/test_subscription_transaction.py