Metadata-Version: 1.0
Name: pirlpay
Version: 0.0.1
Summary: PirlPay API
Home-page: UNKNOWN
Author: UNKNOWN
Author-email: support@pirl.io
License: UNKNOWN
Keywords: PirlPay API
Platform: UNKNOWN
